pysimpler/__init__.py
pysimpler/caches.py
pysimpler/constants.py
pysimpler/enums.py
pysimpler/logger.py
pysimpler/report.py
pysimpler/requirements.txt
pysimpler/timers.py
pysimpler-0.0.8.dist-info/LICENSE
pysimpler-0.0.8.dist-info/METADATA
pysimpler-0.0.8.dist-info/WHEEL
pysimpler-0.0.8.dist-info/top_level.txt
pysimpler-0.0.8.dist-info/RECORD
