Metadata-Version: 2.1
Name: pysimpler
Version: 0.0.8
Summary: pysimpler
Home-page: https://github.com/m-pektas/pysimpler
Author: Muhammed Pektas
Keywords: software engineering,exception,cache,timer,python,decorators
Requires-Python: >=3.7, <4
License-File: LICENSE
Requires-Dist: matplotlib
Requires-Dist: pandas
Requires-Dist: seaborn
